pygitstats/__init__.py
pygitstats/graphql/__init__.py
pygitstats/graphql/gitstats.py
pygitstats-0.1.1.dist-info/LICENSE
pygitstats-0.1.1.dist-info/METADATA
pygitstats-0.1.1.dist-info/WHEEL
pygitstats-0.1.1.dist-info/top_level.txt
pygitstats-0.1.1.dist-info/RECORD
