Metadata-Version: 2.1
Name: pygitstats
Version: 0.1.1
Summary: "A Python wrapper for the GitHub API"
Home-page: https://github.com/DillonB07/GitStats
Author: Dillon Barnes
Author-email: dillonbarnes07@gmail.com
License: UNKNOWN
Project-URL: Documentation, https://github.com/DillonB07/GitStats
Project-URL: Source Code, https://github.com/DillonB07/GitStats
Project-URL: Bug Tracker, https://github.com/DillonB07/GitStats/issues
Project-URL: Discussions, https://github.com/DillonB07/GitStats/discussions
Keywords: dillonb07,utils
Platform: UNKNOWN
Classifier: Programming Language :: Python :: 3
Classifier: License :: OSI Approved :: GNU Lesser General Public License v3 (LGPLv3)
Classifier: Operating System :: OS Independent
Classifier: Topic :: Utilities
Requires-Python: >=3.6
License-File: LICENSE
Requires-Dist: requests
